noggin/__init__.py
noggin/_version.py
noggin/logger.py
noggin/plotter.py
noggin/typing.py
noggin/utils.py
noggin/xarray.py
noggin-0.10.1.dist-info/LICENSE.txt
noggin-0.10.1.dist-info/METADATA
noggin-0.10.1.dist-info/WHEEL
noggin-0.10.1.dist-info/top_level.txt
noggin-0.10.1.dist-info/RECORD
