Metadata-Version: 2.1
Name: noggin
Version: 0.10.1
Summary: A simple tool for logging and plotting measurements when training a neural network.
Home-page: https://github.com/rsokl/noggin
Author: Ryan Soklaski
Author-email: ryan.soklaski@gmail.com
License: MIT
Download-URL: https://github.com/rsokl/noggin/tarball/0.10.1
Platform: UNKNOWN
Classifier: Development Status :: 4 - Beta
Classifier: License :: OSI Approved :: MIT License
Classifier: Operating System :: OS Independent
Classifier: Intended Audience :: Science/Research
Classifier: Intended Audience :: Education
Classifier: Programming Language :: Python
Classifier: Programming Language :: Python :: 3
Classifier: Programming Language :: Python :: 3.6
Classifier: Programming Language :: Python :: 3.7
Classifier: Topic :: Scientific/Engineering
Requires-Python: >=3.6
Requires-Dist: numpy (>=1.9)
Requires-Dist: matplotlib (>=2.0)
Requires-Dist: xarray (>=0.1)
Requires-Dist: custom-inherit (>=2.2)
